[{"date":"2017-08-21","symbol":"AEON","price":9.95224},{"date":"2017-08-21","symbol":"BCN","price":9.6305},{"date":"2017-08-21","symbol":"BTC","price":9.2615291049},{"date":"2017-08-21","symbol":"BNT","price":8.6868},{"date":"2017-08-21","symbol":"DASH","price":9.340100000000001},{"date":"2017-08-21","symbol":"DCT","price":9.53636},{"date":"2017-08-21","symbol":"DNT","price":8.246425},{"date":"2017-08-21","symbol":"DOGE","price":9.966},{"date":"2017-08-21","symbol":"EDG","price":7.3887},{"date":"2017-08-21","symbol":"EOS","price":9.63072},{"date":"2017-08-21","symbol":"ETC","price":9.61071},{"date":"2017-08-21","symbol":"ETH","price":8.74843},{"date":"2017-08-21","symbol":"LSK","price":9.4335},{"date":"2017-08-21","symbol":"LTC","price":9.086},{"date":"2017-08-21","symbol":"MAID","price":9.116},{"date":"2017-08-21","symbol":"NXT","price":9.6068},{"date":"2017-08-21","symbol":"OAX","price":7.09549},{"date":"2017-08-21","symbol":"PLBT","price":8.506720000000001},{"date":"2017-08-21","symbol":"PPC","price":8.48318},{"date":"2017-08-21","symbol":"QAU","price":9.452948399999999},{"date":"2017-08-21","symbol":"SC","price":8.876},{"date":"2017-08-21","symbol":"SNC","price":8.927463300000001},{"date":"2017-08-21","symbol":"STRAT","price":9.14624},{"date":"2017-08-21","symbol":"STX","price":9.04239},{"date":"2017-08-21","symbol":"XDN","price":8.7209},{"date":"2017-08-21","symbol":"XEM","price":9.3366},{"date":"2017-08-21","symbol":"XMR","price":9.03},{"date":"2017-08-21","symbol":"XRP","price":11.2468},{"date":"2017-08-21","symbol":"ZEC","price":8.4412},{"date":"2017-08-21","symbol":"ZRC","price":7.88608},{"date":"2017-08-21","symbol":"ZRX","price":10.6594668},{"date":"2017-08-22","symbol":"AEON","price":10.533800000000001},{"date":"2017-08-22","symbol":"BCN","price":11.2795},{"date":"2017-08-22","symbol":"BTC","price":10.386928940899999},{"date":"2017-08-22","symbol":"BNT","price":9.2682},{"date":"2017-08-22","symbol":"DASH","price":10.269700000000002},{"date":"2017-08-22","symbol":"DCT","price":11.098350000000002},{"date":"2017-08-22","symbol":"DNT","price":7.109975},{"date":"2017-08-22","symbol":"DOGE","price":10.308},{"date":"2017-08-22","symbol":"EDG","price":7.9134},{"date":"2017-08-22","symbol":"EOS","price":10.759319999999999},{"date":"2017-08-22","symbol":"ETC","price":11.48238},{"date":"2017-08-22","symbol":"ETH","price":9.28725},{"date":"2017-08-22","symbol":"LSK","price":9.9962},{"date":"2017-08-22","symbol":"LTC","price":9.522},{"date":"2017-08-22","symbol":"MAID","price":9.754000000000001},{"date":"2017-08-22","symbol":"NXT","price":11.7782},{"date":"2017-08-22","symbol":"OAX","price":7.1513599999999995},{"date":"2017-08-22","symbol":"PLBT","price":9.51622},{"date":"2017-08-22","symbol":"PPC","price":9.49442},{"date":"2017-08-22","symbol":"QAU","price":10.992902399999998},{"date":"2017-08-22","symbol":"SC","price":9.955400000000001},{"date":"2017-08-22","symbol":"SNC","price":8.0358456},{"date":"2017-08-22","symbol":"STRAT","price":11.10088},{"date":"2017-08-22","symbol":"STX","price":9.45909},{"date":"2017-08-22","symbol":"XDN","price":8.362},{"date":"2017-08-22","symbol":"XEM","price":9.648200000000001},{"date":"2017-08-22","symbol":"XMR","price":10.9872},{"date":"2017-08-22","symbol":"XRP","price":17.738200000000003},{"date":"2017-08-22","symbol":"ZEC","price":9.3348},{"date":"2017-08-22","symbol":"ZRC","price":8.432640000000001},{"date":"2017-08-22","symbol":"ZRX","price":11.111329399999999},{"date":"2017-08-23","symbol":"AEON","price":9.2566},{"date":"2017-08-23","symbol":"BCN","price":11.883},{"date":"2017-08-23","symbol":"BTC","price":10.338431459},{"date":"2017-08-23","symbol":"BNT","price":8.9946},{"date":"2017-08-23","symbol":"DASH","price":10.2753},{"date":"2017-08-23","symbol":"DCT","price":10.276250000000001},{"date":"2017-08-23","symbol":"DNT","price":7.258},{"date":"2017-08-23","symbol":"DOGE","price":10.32},{"date":"2017-08-23","symbol":"EDG","price":7.8177},{"date":"2017-08-23","symbol":"EOS","price":10.23264},{"date":"2017-08-23","symbol":"ETC","price":10.767359999999998},{"date":"2017-08-23","symbol":"ETH","price":9.25535},{"date":"2017-08-23","symbol":"LSK","price":11.1878},{"date":"2017-08-23","symbol":"LTC","price":10.366},{"date":"2017-08-23","symbol":"MAID","price":9.358},{"date":"2017-08-23","symbol":"NXT","price":11.186},{"date":"2017-08-23","symbol":"OAX","price":6.8720099999999995},{"date":"2017-08-23","symbol":"PLBT","price":9.30086},{"date":"2017-08-23","symbol":"PPC","price":9.32588},{"date":"2017-08-23","symbol":"QAU","price":10.702680299999999},{"date":"2017-08-23","symbol":"SC","price":9.8504},{"date":"2017-08-23","symbol":"SNC","price":8.238999},{"date":"2017-08-23","symbol":"STRAT","price":11.08244},{"date":"2017-08-23","symbol":"STX","price":9.29241},{"date":"2017-08-23","symbol":"XDN","price":8.472999999999999},{"date":"2017-08-23","symbol":"XEM","price":9.443},{"date":"2017-08-23","symbol":"XMR","price":10.568399999999999},{"date":"2017-08-23","symbol":"XRP","price":16.0208},{"date":"2017-08-23","symbol":"ZEC","price":9.1016},{"date":"2017-08-23","symbol":"ZRC","price":7.88608},{"date":"2017-08-23","symbol":"ZRX","price":10.9064476},{"date":"2017-08-24","symbol":"AEON","price":10.423440000000001},{"date":"2017-08-24","symbol":"BCN","price":12.0275},{"date":"2017-08-24","symbol":"BTC","price":10.7594631055},{"date":"2017-08-24","symbol":"BNT","price":9.370800000000001},{"date":"2017-08-24","symbol":"DASH","price":10.605350000000001},{"date":"2017-08-24","symbol":"DCT","price":10.76951},{"date":"2017-08-24","symbol":"DNT","price":7.119525},{"date":"2017-08-24","symbol":"DOGE","price":10.74},{"date":"2017-08-24","symbol":"EDG","price":7.9926},{"date":"2017-08-24","symbol":"EOS","price":10.68408},{"date":"2017-08-24","symbol":"ETC","price":10.69726},{"date":"2017-08-24","symbol":"ETH","price":9.419780000000001},{"date":"2017-08-24","symbol":"LSK","price":12.8428},{"date":"2017-08-24","symbol":"LTC","price":10.106000000000002},{"date":"2017-08-24","symbol":"MAID","price":9.92},{"date":"2017-08-24","symbol":"NXT","price":11.4774},{"date":"2017-08-24","symbol":"OAX","price":6.25744},{"date":"2017-08-24","symbol":"PLBT","price":9.61044},{"date":"2017-08-24","symbol":"PPC","price":9.66296},{"date":"2017-08-24","symbol":"QAU","price":11.0402856},{"date":"2017-08-24","symbol":"SC","price":9.7664},{"date":"2017-08-24","symbol":"SNC","price":8.2502853},{"date":"2017-08-24","symbol":"STRAT","price":11.10088},{"date":"2017-08-24","symbol":"STX","price":10.16748},{"date":"2017-08-24","symbol":"XDN","price":8.495199999999999},{"date":"2017-08-24","symbol":"XEM","price":9.842},{"date":"2017-08-24","symbol":"XMR","price":10.278},{"date":"2017-08-24","symbol":"XRP","price":13.361},{"date":"2017-08-24","symbol":"ZEC","price":9.1972},{"date":"2017-08-24","symbol":"ZRC","price":9.44768},{"date":"2017-08-24","symbol":"ZRX","price":11.986988599999998},{"date":"2017-08-25","symbol":"AEON","price":9.42648},{"date":"2017-08-25","symbol":"BCN","price":11.551499999999999},{"date":"2017-08-25","symbol":"BTC","price":10.8734433625},{"date":"2017-08-25","symbol":"BNT","price":9.234},{"date":"2017-08-25","symbol":"DASH","price":11.00155},{"date":"2017-08-25","symbol":"DCT","price":10.02962},{"date":"2017-08-25","symbol":"DNT","price":5.963975},{"date":"2017-08-25","symbol":"DOGE","price":10.512},{"date":"2017-08-25","symbol":"EDG","price":8.1829},{"date":"2017-08-25","symbol":"EOS","price":10.30788},{"date":"2017-08-25","symbol":"ETC","price":10.641179999999999},{"date":"2017-08-25","symbol":"ETH","price":9.605960000000001},{"date":"2017-08-25","symbol":"LSK","price":14.3323},{"date":"2017-08-25","symbol":"LTC","price":10.234000000000002},{"date":"2017-08-25","symbol":"MAID","price":10.922},{"date":"2017-08-25","symbol":"NXT","price":10.6126},{"date":"2017-08-25","symbol":"OAX","price":5.92222},{"date":"2017-08-25","symbol":"PLBT","price":8.870140000000001},{"date":"2017-08-25","symbol":"PPC","price":11.573080000000001},{"date":"2017-08-25","symbol":"QAU","price":11.0580543},{"date":"2017-08-25","symbol":"SC","price":9.6852},{"date":"2017-08-25","symbol":"SNC","price":8.33718981},{"date":"2017-08-25","symbol":"STRAT","price":11.027120000000002},{"date":"2017-08-25","symbol":"STX","price":11.459249999999999},{"date":"2017-08-25","symbol":"XDN","price":8.299100000000001},{"date":"2017-08-25","symbol":"XEM","price":9.7356},{"date":"2017-08-25","symbol":"XMR","price":12.8244},{"date":"2017-08-25","symbol":"XRP","price":13.4292},{"date":"2017-08-25","symbol":"ZEC","price":9.5168},{"date":"2017-08-25","symbol":"ZRC","price":11.712},{"date":"2017-08-25","symbol":"ZRX","price":10.485457599999998},{"date":"2017-08-26","symbol":"AEON","price":12.772},{"date":"2017-08-26","symbol":"BCN","price":12.376000000000001},{"date":"2017-08-26","symbol":"BTC","price":10.8100465006},{"date":"2017-08-26","symbol":"BNT","price":10.0548},{"date":"2017-08-26","symbol":"DASH","price":12.68365},{"date":"2017-08-26","symbol":"DCT","price":10.02962},{"date":"2017-08-26","symbol":"DNT","price":6.527424999999999},{"date":"2017-08-26","symbol":"DOGE","price":10.446},{"date":"2017-08-26","symbol":"EDG","price":8.184},{"date":"2017-08-26","symbol":"EOS","price":10.08216},{"date":"2017-08-26","symbol":"ETC","price":11.061779999999999},{"date":"2017-08-26","symbol":"ETH","price":9.736170000000001},{"date":"2017-08-26","symbol":"LSK","price":26.0828},{"date":"2017-08-26","symbol":"LTC","price":12.174},{"date":"2017-08-26","symbol":"MAID","price":12.267999999999999},{"date":"2017-08-26","symbol":"NXT","price":10.199},{"date":"2017-08-26","symbol":"OAX","price":6.03396},{"date":"2017-08-26","symbol":"PLBT","price":8.412500000000001},{"date":"2017-08-26","symbol":"PPC","price":11.404539999999999},{"date":"2017-08-26","symbol":"QAU","price":12.5447022},{"date":"2017-08-26","symbol":"SC","price":10.178},{"date":"2017-08-26","symbol":"SNC","price":6.6307012499999995},{"date":"2017-08-26","symbol":"STRAT","price":12.48388},{"date":"2017-08-26","symbol":"STX","price":7.917299999999999},{"date":"2017-08-26","symbol":"XDN","price":8.3694},{"date":"2017-08-26","symbol":"XEM","price":10.241000000000001},{"date":"2017-08-26","symbol":"XMR","price":15.682799999999999},{"date":"2017-08-26","symbol":"XRP","price":12.4806},{"date":"2017-08-26","symbol":"ZEC","price":10.6928},{"date":"2017-08-26","symbol":"ZRC","price":12.805119999999999},{"date":"2017-08-26","symbol":"ZRX","price":9.5340202},{"date":"2017-08-27","symbol":"AEON","price":13.268},{"date":"2017-08-27","symbol":"BCN","price":12.452499999999999},{"date":"2017-08-27","symbol":"BTC","price":10.807290115299999},{"date":"2017-08-27","symbol":"BNT","price":10.1916},{"date":"2017-08-27","symbol":"DASH","price":12.754},{"date":"2017-08-27","symbol":"DCT","price":9.78299},{"date":"2017-08-27","symbol":"DNT","price":6.33165},{"date":"2017-08-27","symbol":"DOGE","price":10.704},{"date":"2017-08-27","symbol":"EDG","price":7.942},{"date":"2017-08-27","symbol":"EOS","price":10.006920000000001},{"date":"2017-08-27","symbol":"ETC","price":11.293109999999999},{"date":"2017-08-27","symbol":"ETH","price":9.88407},{"date":"2017-08-27","symbol":"LSK","price":25.619400000000002},{"date":"2017-08-27","symbol":"LTC","price":12.286000000000001},{"date":"2017-08-27","symbol":"MAID","price":12.058},{"date":"2017-08-27","symbol":"NXT","price":11.082600000000001},{"date":"2017-08-27","symbol":"OAX","price":5.587},{"date":"2017-08-27","symbol":"PLBT","price":10.687240000000001},{"date":"2017-08-27","symbol":"PPC","price":10.89892},{"date":"2017-08-27","symbol":"QAU","price":12.615777},{"date":"2017-08-27","symbol":"SC","price":11.271400000000002},{"date":"2017-08-27","symbol":"SNC","price":6.88577163},{"date":"2017-08-27","symbol":"STRAT","price":13.258360000000001},{"date":"2017-08-27","symbol":"STX","price":7.54227},{"date":"2017-08-27","symbol":"XDN","price":8.769},{"date":"2017-08-27","symbol":"XEM","price":10.366399999999999},{"date":"2017-08-27","symbol":"XMR","price":15.6564},{"date":"2017-08-27","symbol":"XRP","price":12.536399999999999},{"date":"2017-08-27","symbol":"ZEC","price":11.0576},{"date":"2017-08-27","symbol":"ZRC","price":12.41472},{"date":"2017-08-27","symbol":"ZRX","price":9.8708122},{"date":"2017-08-28","symbol":"AEON","price":13.020000000000001},{"date":"2017-08-28","symbol":"BCN","price":13.872},{"date":"2017-08-28","symbol":"BTC","price":10.873915176199999},{"date":"2017-08-28","symbol":"BNT","price":10.089},{"date":"2017-08-28","symbol":"DASH","price":12.382650000000002},{"date":"2017-08-28","symbol":"DCT","price":9.70078},{"date":"2017-08-28","symbol":"DNT","price":6.250475},{"date":"2017-08-28","symbol":"DOGE","price":10.716000000000001},{"date":"2017-08-28","symbol":"EDG","price":8.6603},{"date":"2017-08-28","symbol":"EOS","price":10.006920000000001},{"date":"2017-08-28","symbol":"ETC","price":11.047759999999998},{"date":"2017-08-28","symbol":"ETH","price":10.063},{"date":"2017-08-28","symbol":"LSK","price":21.6474},{"date":"2017-08-28","symbol":"LTC","price":12.484000000000002},{"date":"2017-08-28","symbol":"MAID","price":12.822},{"date":"2017-08-28","symbol":"NXT","price":10.622},{"date":"2017-08-28","symbol":"OAX","price":5.3825158},{"date":"2017-08-28","symbol":"PLBT","price":8.82976},{"date":"2017-08-28","symbol":"PPC","price":11.348360000000001},{"date":"2017-08-28","symbol":"QAU","price":12.852693},{"date":"2017-08-28","symbol":"SC","price":12.2612},{"date":"2017-08-28","symbol":"SNC","price":6.42529059},{"date":"2017-08-28","symbol":"STRAT","price":13.38744},{"date":"2017-08-28","symbol":"STX","price":6.62553},{"date":"2017-08-28","symbol":"XDN","price":10.1343},{"date":"2017-08-28","symbol":"XEM","price":10.5944},{"date":"2017-08-28","symbol":"XMR","price":16.9788},{"date":"2017-08-28","symbol":"XRP","price":14.012},{"date":"2017-08-28","symbol":"ZEC","price":10.998800000000001},{"date":"2017-08-28","symbol":"ZRC","price":13.89824},{"date":"2017-08-28","symbol":"ZRX","price":9.6996096},{"date":"2017-08-29","symbol":"AEON","price":11.93872},{"date":"2017-08-29","symbol":"BCN","price":16.388},{"date":"2017-08-29","symbol":"BTC","price":11.4290909073},{"date":"2017-08-29","symbol":"BNT","price":11.012400000000001},{"date":"2017-08-29","symbol":"DASH","price":12.482750000000001},{"date":"2017-08-29","symbol":"DCT","price":10.11183},{"date":"2017-08-29","symbol":"DNT","price":5.362325},{"date":"2017-08-29","symbol":"DOGE","price":11.424000000000001},{"date":"2017-08-29","symbol":"EDG","price":7.9639999999999995},{"date":"2017-08-29","symbol":"EOS","price":9.93168},{"date":"2017-08-29","symbol":"ETC","price":11.166929999999999},{"date":"2017-08-29","symbol":"ETH","price":10.852380000000002},{"date":"2017-08-29","symbol":"LSK","price":20.091700000000003},{"date":"2017-08-29","symbol":"LTC","price":12.66},{"date":"2017-08-29","symbol":"MAID","price":12.432},{"date":"2017-08-29","symbol":"NXT","price":10.3024},{"date":"2017-08-29","symbol":"OAX","price":4.456191199999999},{"date":"2017-08-29","symbol":"PLBT","price":9.152800000000001},{"date":"2017-08-29","symbol":"PPC","price":11.12364},{"date":"2017-08-29","symbol":"QAU","price":13.8536631},{"date":"2017-08-29","symbol":"SC","price":11.2756},{"date":"2017-08-29","symbol":"SNC","price":7.306750620000001},{"date":"2017-08-29","symbol":"STRAT","price":12.70516},{"date":"2017-08-29","symbol":"STX","price":7.833959999999999},{"date":"2017-08-29","symbol":"XDN","price":9.1316},{"date":"2017-08-29","symbol":"XEM","price":10.7274},{"date":"2017-08-29","symbol":"XMR","price":16.0752},{"date":"2017-08-29","symbol":"XRP","price":13.5408},{"date":"2017-08-29","symbol":"ZEC","price":10.8012},{"date":"2017-08-29","symbol":"ZRC","price":12.805119999999999},{"date":"2017-08-29","symbol":"ZRX","price":10.286189},{"date":"2017-08-30","symbol":"AEON","price":11.41172},{"date":"2017-08-30","symbol":"BCN","price":23.4175},{"date":"2017-08-30","symbol":"BTC","price":11.3812638975},{"date":"2017-08-30","symbol":"BNT","price":10.8756},{"date":"2017-08-30","symbol":"DASH","price":12.878950000000001},{"date":"2017-08-30","symbol":"DCT","price":9.78299},{"date":"2017-08-30","symbol":"DNT","price":5.2716},{"date":"2017-08-30","symbol":"DOGE","price":12.648},{"date":"2017-08-30","symbol":"EDG","price":7.9002},{"date":"2017-08-30","symbol":"EOS","price":9.48024},{"date":"2017-08-30","symbol":"ETC","price":11.13889},{"date":"2017-08-30","symbol":"ETH","price":11.1853},{"date":"2017-08-30","symbol":"LSK","price":22.0115},{"date":"2017-08-30","symbol":"LTC","price":12.764000000000001},{"date":"2017-08-30","symbol":"MAID","price":13.058},{"date":"2017-08-30","symbol":"NXT","price":10.631400000000001},{"date":"2017-08-30","symbol":"OAX","price":5.0294174},{"date":"2017-08-30","symbol":"PLBT","price":9.422},{"date":"2017-08-30","symbol":"PPC","price":10.6742},{"date":"2017-08-30","symbol":"QAU","price":14.1971913},{"date":"2017-08-30","symbol":"SC","price":12.3844},{"date":"2017-08-30","symbol":"SNC","price":6.7040622},{"date":"2017-08-30","symbol":"STRAT","price":13.47964},{"date":"2017-08-30","symbol":"STX","price":5.95881},{"date":"2017-08-30","symbol":"XDN","price":9.3129},{"date":"2017-08-30","symbol":"XEM","price":11.346799999999998},{"date":"2017-08-30","symbol":"XMR","price":16.0548},{"date":"2017-08-30","symbol":"XRP","price":14.2104},{"date":"2017-08-30","symbol":"ZEC","price":11.0492},{"date":"2017-08-30","symbol":"ZRC","price":12.336640000000001},{"date":"2017-08-30","symbol":"ZRX","price":9.424562799999999},{"date":"2017-08-31","symbol":"AEON","price":10.87976},{"date":"2017-08-31","symbol":"BCN","price":20.2725},{"date":"2017-08-31","symbol":"BTC","price":11.7706840261},{"date":"2017-08-31","symbol":"BNT","price":10.8414},{"date":"2017-08-31","symbol":"DASH","price":13.3574},{"date":"2017-08-31","symbol":"DCT","price":9.8652},{"date":"2017-08-31","symbol":"DNT","price":5.051950000000001},{"date":"2017-08-31","symbol":"DOGE","price":12.6},{"date":"2017-08-31","symbol":"EDG","price":9.098099999999999},{"date":"2017-08-31","symbol":"EOS","price":9.856440000000001},{"date":"2017-08-31","symbol":"ETC","price":11.7067},{"date":"2017-08-31","symbol":"ETH","price":11.254900000000001},{"date":"2017-08-31","symbol":"LSK","price":23.2362},{"date":"2017-08-31","symbol":"LTC","price":14.674000000000001},{"date":"2017-08-31","symbol":"MAID","price":12.951999999999998},{"date":"2017-08-31","symbol":"NXT","price":10.575000000000001},{"date":"2017-08-31","symbol":"OAX","price":4.1472301},{"date":"2017-08-31","symbol":"PLBT","price":9.677740000000002},{"date":"2017-08-31","symbol":"PPC","price":11.5169},{"date":"2017-08-31","symbol":"QAU","price":14.2919577},{"date":"2017-08-31","symbol":"SC","price":11.8118},{"date":"2017-08-31","symbol":"SNC","price":5.69393835},{"date":"2017-08-31","symbol":"STRAT","price":13.62716},{"date":"2017-08-31","symbol":"STX","price":5.7504599999999995},{"date":"2017-08-31","symbol":"XDN","price":10.922400000000001},{"date":"2017-08-31","symbol":"XEM","price":12.828800000000001},{"date":"2017-08-31","symbol":"XMR","price":17.0688},{"date":"2017-08-31","symbol":"XRP","price":16.0394},{"date":"2017-08-31","symbol":"ZEC","price":11.4548},{"date":"2017-08-31","symbol":"ZRC","price":13.50784},{"date":"2017-08-31","symbol":"ZRX","price":9.7894208},{"date":"2017-09-01","symbol":"AEON","price":13.640000000000002},{"date":"2017-09-01","symbol":"BCN","price":20.646500000000003},{"date":"2017-09-01","symbol":"BTC","price":12.120173816300001},{"date":"2017-09-01","symbol":"BNT","price":11.0466},{"date":"2017-09-01","symbol":"DASH","price":13.791400000000001},{"date":"2017-09-01","symbol":"DCT","price":10.358460000000001},{"date":"2017-09-01","symbol":"DNT","price":4.290814999999999},{"date":"2017-09-01","symbol":"DOGE","price":14.946000000000002},{"date":"2017-09-01","symbol":"EDG","price":9.5194},{"date":"2017-09-01","symbol":"EOS","price":9.93168},{"date":"2017-09-01","symbol":"ETC","price":15.372929999999998},{"date":"2017-09-01","symbol":"ETH","price":11.323630000000001},{"date":"2017-09-01","symbol":"LSK","price":24.3947},{"date":"2017-09-01","symbol":"LTC","price":17.072},{"date":"2017-09-01","symbol":"MAID","price":13.97},{"date":"2017-09-01","symbol":"NXT","price":11.0356},{"date":"2017-09-01","symbol":"OAX","price":4.3796493},{"date":"2017-09-01","symbol":"PLBT","price":9.23356},{"date":"2017-09-01","symbol":"PPC","price":11.74162},{"date":"2017-09-01","symbol":"QAU","price":14.108347799999999},{"date":"2017-09-01","symbol":"SC","price":12.436200000000001},{"date":"2017-09-01","symbol":"SNC","price":7.573107300000001},{"date":"2017-09-01","symbol":"STRAT","price":13.22148},{"date":"2017-09-01","symbol":"STX","price":5.45877},{"date":"2017-09-01","symbol":"XDN","price":11.0741},{"date":"2017-09-01","symbol":"XEM","price":12.3538},{"date":"2017-09-01","symbol":"XMR","price":17.023200000000003},{"date":"2017-09-01","symbol":"XRP","price":15.741800000000001},{"date":"2017-09-01","symbol":"ZEC","price":12.3724},{"date":"2017-09-01","symbol":"ZRC","price":13.664},{"date":"2017-09-01","symbol":"ZRX","price":10.471424599999999},{"date":"2017-09-02","symbol":"AEON","price":11.14016},{"date":"2017-09-02","symbol":"BCN","price":17.102},{"date":"2017-09-02","symbol":"BTC","price":11.104507914},{"date":"2017-09-02","symbol":"BNT","price":9.6102},{"date":"2017-09-02","symbol":"DASH","price":11.949},{"date":"2017-09-02","symbol":"DCT","price":9.289729999999999},{"date":"2017-09-02","symbol":"DNT","price":3.9030849999999995},{"date":"2017-09-02","symbol":"DOGE","price":13.074},{"date":"2017-09-02","symbol":"EDG","price":8.1851},{"date":"2017-09-02","symbol":"EOS","price":9.0288},{"date":"2017-09-02","symbol":"ETC","price":13.24189},{"date":"2017-09-02","symbol":"ETH","price":9.79881},{"date":"2017-09-02","symbol":"LSK","price":21.7798},{"date":"2017-09-02","symbol":"LTC","price":15.25},{"date":"2017-09-02","symbol":"MAID","price":12.968},{"date":"2017-09-02","symbol":"NXT","price":9.87},{"date":"2017-09-02","symbol":"OAX","price":3.9874419},{"date":"2017-09-02","symbol":"PLBT","price":8.42596},{"date":"2017-09-02","symbol":"PPC","price":10.73038},{"date":"2017-09-02","symbol":"QAU","price":12.4084755},{"date":"2017-09-02","symbol":"SC","price":11.6452},{"date":"2017-09-02","symbol":"SNC","price":5.37679332},{"date":"2017-09-02","symbol":"STRAT","price":11.32216},{"date":"2017-09-02","symbol":"STX","price":4.75038},{"date":"2017-09-02","symbol":"XDN","price":9.7606},{"date":"2017-09-02","symbol":"XEM","price":10.9782},{"date":"2017-09-02","symbol":"XMR","price":14.7708},{"date":"2017-09-02","symbol":"XRP","price":13.8136},{"date":"2017-09-02","symbol":"ZEC","price":9.8636},{"date":"2017-09-02","symbol":"ZRC","price":11.712},{"date":"2017-09-02","symbol":"ZRX","price":8.672393999999999},{"date":"2017-09-03","symbol":"AEON","price":9.7774},{"date":"2017-09-03","symbol":"BCN","price":18.929499999999997},{"date":"2017-09-03","symbol":"BTC","price":11.383424307599999},{"date":"2017-09-03","symbol":"BNT","price":9.7128},{"date":"2017-09-03","symbol":"DASH","price":12.443200000000001},{"date":"2017-09-03","symbol":"DCT","price":9.454149999999998},{"date":"2017-09-03","symbol":"DNT","price":4.3581425000000005},{"date":"2017-09-03","symbol":"DOGE","price":12.851999999999999},{"date":"2017-09-03","symbol":"EDG","price":8.4315},{"date":"2017-09-03","symbol":"EOS","price":9.63072},{"date":"2017-09-03","symbol":"ETC","price":13.564350000000001},{"date":"2017-09-03","symbol":"ETH","price":10.14536},{"date":"2017-09-03","symbol":"LSK","price":23.633399999999998},{"date":"2017-09-03","symbol":"LTC","price":15.846000000000002},{"date":"2017-09-03","symbol":"MAID","price":13.39},{"date":"2017-09-03","symbol":"NXT","price":10.058},{"date":"2017-09-03","symbol":"OAX","price":4.0595142},{"date":"2017-09-03","symbol":"PLBT","price":8.3452},{"date":"2017-09-03","symbol":"PPC","price":10.56184},{"date":"2017-09-03","symbol":"QAU","price":13.563441000000001},{"date":"2017-09-03","symbol":"SC","price":12.0652},{"date":"2017-09-03","symbol":"SNC","price":5.167996769999999},{"date":"2017-09-03","symbol":"STRAT","price":12.022879999999999},{"date":"2017-09-03","symbol":"STX","price":4.8753899999999994},{"date":"2017-09-03","symbol":"XDN","price":9.9419},{"date":"2017-09-03","symbol":"XEM","price":11.403799999999999},{"date":"2017-09-03","symbol":"XMR","price":15.011999999999999},{"date":"2017-09-03","symbol":"XRP","price":14.2352},{"date":"2017-09-03","symbol":"ZEC","price":10.5},{"date":"2017-09-03","symbol":"ZRC","price":12.02432},{"date":"2017-09-03","symbol":"ZRX","price":8.195272},{"date":"2017-09-04","symbol":"AEON","price":10.37508},{"date":"2017-09-04","symbol":"BCN","price":15.9205},{"date":"2017-09-04","symbol":"BTC","price":10.7159569159},{"date":"2017-09-04","symbol":"BNT","price":8.276399999999999},{"date":"2017-09-04","symbol":"DASH","price":11.3449},{"date":"2017-09-04","symbol":"DCT","price":7.4572691},{"date":"2017-09-04","symbol":"DNT","price":3.3114624999999998},{"date":"2017-09-04","symbol":"DOGE","price":11.43},{"date":"2017-09-04","symbol":"EDG","price":7.181900000000001},{"date":"2017-09-04","symbol":"EOS","price":7.2636696},{"date":"2017-09-04","symbol":"ETC","price":11.93803},{"date":"2017-09-04","symbol":"ETH","price":8.97898},{"date":"2017-09-04","symbol":"LSK","price":22.938299999999998},{"date":"2017-09-04","symbol":"LTC","price":14.124000000000002},{"date":"2017-09-04","symbol":"MAID","price":11.224},{"date":"2017-09-04","symbol":"NXT","price":8.6386},{"date":"2017-09-04","symbol":"OAX","price":3.1918531},{"date":"2017-09-04","symbol":"PLBT","price":8.12984},{"date":"2017-09-04","symbol":"PPC","price":8.820260000000001},{"date":"2017-09-04","symbol":"QAU","price":12.7638495},{"date":"2017-09-04","symbol":"SC","price":10.2102},{"date":"2017-09-04","symbol":"SNC","price":4.98628734},{"date":"2017-09-04","symbol":"STRAT","price":10.67676},{"date":"2017-09-04","symbol":"STX","price":3.8265561},{"date":"2017-09-04","symbol":"XDN","price":8.891100000000002},{"date":"2017-09-04","symbol":"XEM","price":10.5412},{"date":"2017-09-04","symbol":"XMR","price":13.0224},{"date":"2017-09-04","symbol":"XRP","price":13.032399999999999},{"date":"2017-09-04","symbol":"ZEC","price":9.114400000000002},{"date":"2017-09-04","symbol":"ZRC","price":11.86816},{"date":"2017-09-04","symbol":"ZRX","price":7.2157686},{"date":"2017-09-05","symbol":"AEON","price":11.49108},{"date":"2017-09-05","symbol":"BCN","price":16.7195},{"date":"2017-09-05","symbol":"BTC","price":11.1013045473},{"date":"2017-09-05","symbol":"BNT","price":8.721},{"date":"2017-09-05","symbol":"DASH","price":11.53985},{"date":"2017-09-05","symbol":"DCT","price":7.8025511000000005},{"date":"2017-09-05","symbol":"DNT","price":3.4155575},{"date":"2017-09-05","symbol":"DOGE","price":12.3},{"date":"2017-09-05","symbol":"EDG","price":7.203900000000001},{"date":"2017-09-05","symbol":"EOS","price":6.571461599999999},{"date":"2017-09-05","symbol":"ETC","price":12.022149999999998},{"date":"2017-09-05","symbol":"ETH","price":9.32611},{"date":"2017-09-05","symbol":"LSK","price":22.4749},{"date":"2017-09-05","symbol":"LTC","price":14.725999999999999},{"date":"2017-09-05","symbol":"MAID","price":12.678},{"date":"2017-09-05","symbol":"NXT","price":8.67902},{"date":"2017-09-05","symbol":"OAX","price":2.7772976999999996},{"date":"2017-09-05","symbol":"PLBT","price":8.85668},{"date":"2017-09-05","symbol":"PPC","price":9.887680000000001},{"date":"2017-09-05","symbol":"QAU","price":14.2801119},{"date":"2017-09-05","symbol":"SC","price":11.0152},{"date":"2017-09-05","symbol":"SNC","price":5.709739170000001},{"date":"2017-09-05","symbol":"STRAT","price":11.39592},{"date":"2017-09-05","symbol":"STX","price":4.20867},{"date":"2017-09-05","symbol":"XDN","price":9.5941},{"date":"2017-09-05","symbol":"XEM","price":11.171999999999999},{"date":"2017-09-05","symbol":"XMR","price":14.372399999999999},{"date":"2017-09-05","symbol":"XRP","price":13.3982},{"date":"2017-09-05","symbol":"ZEC","price":9.267999999999999},{"date":"2017-09-05","symbol":"ZRC","price":11.47776},{"date":"2017-09-05","symbol":"ZRX","price":6.9659812},{"date":"2017-09-06","symbol":"AEON","price":11.8296},{"date":"2017-09-06","symbol":"BCN","price":16.9575},{"date":"2017-09-06","symbol":"BTC","price":11.4890112472},{"date":"2017-09-06","symbol":"BNT","price":9.234},{"date":"2017-09-06","symbol":"DASH","price":12.211500000000001},{"date":"2017-09-06","symbol":"DCT","price":7.431784},{"date":"2017-09-06","symbol":"DNT","price":3.4685599999999996},{"date":"2017-09-06","symbol":"DOGE","price":12.366},{"date":"2017-09-06","symbol":"EDG","price":7.4613000000000005},{"date":"2017-09-06","symbol":"EOS","price":6.9092892},{"date":"2017-09-06","symbol":"ETC","price":13.41714},{"date":"2017-09-06","symbol":"ETH","price":9.78228},{"date":"2017-09-06","symbol":"LSK","price":23.6996},{"date":"2017-09-06","symbol":"LTC","price":16.344},{"date":"2017-09-06","symbol":"MAID","price":13.11},{"date":"2017-09-06","symbol":"NXT","price":9.8042},{"date":"2017-09-06","symbol":"OAX","price":2.9030051999999995},{"date":"2017-09-06","symbol":"PLBT","price":8.91052},{"date":"2017-09-06","symbol":"PPC","price":11.12364},{"date":"2017-09-06","symbol":"QAU","price":14.8131729},{"date":"2017-09-06","symbol":"SC","price":11.4646},{"date":"2017-09-06","symbol":"SNC","price":5.74924122},{"date":"2017-09-06","symbol":"STRAT","price":11.46968},{"date":"2017-09-06","symbol":"STX","price":4.917059999999999},{"date":"2017-09-06","symbol":"XDN","price":10.0381},{"date":"2017-09-06","symbol":"XEM","price":11.460799999999999},{"date":"2017-09-06","symbol":"XMR","price":14.9016},{"date":"2017-09-06","symbol":"XRP","price":14.2662},{"date":"2017-09-06","symbol":"ZEC","price":10.0036},{"date":"2017-09-06","symbol":"ZRC","price":10.853119999999999},{"date":"2017-09-06","symbol":"ZRX","price":7.263480799999999}]